{
    "name": "cloud_2_972",
    "num_nodes": 20,
    "num_leaves": 1,
    "providers": {
        "provider_0": {
            "name": "aws",
            "leave": true,
            "estimated_latency": [
                0.0,
                4.913254887579381,
                0.19321407210113883,
                0.37528331588039454,
                6.898342004956611,
                3.071415102604752,
                2.224434495806129,
                2.1857169362984155,
                5.974003359921145,
                2.050858512831408,
                9.157527752297822,
                0.11642745187870386,
                8.778253456247805,
                4.956947445129021,
                0.5956995319512612,
                3.3330816931343876,
                7.41201395441531,
                8.321044959453708,
                0.6622609517256514,
                7.904723505308349
            ],
            "pricing_Storage_Transfer": 0,
            "max_RAM_curr": 0.15088520370842903,
            "pricing_RAM": 5,
            "pricing_data_sent": 0.01,
            "pricing_StartRequest": 4e-07
        },
        "provider_1": {
            "name": "aws",
            "estimated_latency": [
                4.913254887579381,
                0.0,
                9.838982652919139,
                1.351287017709642,
                3.08410382983651,
                9.547265978730186,
                6.190864162011232,
                5.999849787748343,
                2.7423515665871196,
                5.316733694416127,
                8.66751772120346,
                9.485317839754005,
                3.275492709382568,
                5.2716068705493155,
                0.7938375308987066,
                6.467368830119085,
                5.683384715697545,
                3.5913359401305947,
                4.49328018623961,
                7.413337126200206
            ],
            "leave": false,
            "pricing_Storage_Transfer": 0,
            "max_RAM_curr": 0.246450961447023,
            "pricing_RAM": 5,
            "pricing_data_sent": 0.01,
            "pricing_StartRequest": 4e-07
        },
        "provider_2": {
            "name": "aws",
            "estimated_latency": [
                0.19321407210113883,
                9.838982652919139,
                0.0,
                6.886724071892964,
                1.2283059977652089,
                3.288775687533392,
                0.6829028580977299,
                1.2318339499227677,
                1.1384306640851418,
                3.5496839006193937,
                9.006394539031264,
                4.008572801325589,
                0.24522460889579084,
                9.14990688496163,
                7.604470397022694,
                5.325453518380833,
                7.453164886055443,
                2.8703160874485936,
                5.965091116712954,
                6.9016572639632905
            ],
            "leave": false,
            "pricing_Storage_Transfer": 0,
            "max_RAM_curr": 0.030227236197227392,
            "pricing_RAM": 5,
            "pricing_data_sent": 0.01,
            "pricing_StartRequest": 4e-07
        },
        "provider_3": {
            "name": "aws",
            "estimated_latency": [
                0.37528331588039454,
                1.351287017709642,
                6.886724071892964,
                0.0,
                8.010150580222954,
                9.873289365457767,
                7.237073485535988,
                9.164290593680695,
                2.312388837597407,
                4.518653751519471,
                4.655016612812897,
                7.6888148018175695,
                0.7372178222207624,
                1.233327018747446,
                5.92709641101848,
                0.6177142019908013,
                2.388749542836553,
                5.920805021254816,
                4.600613683620065,
                0.5833377533544383
            ],
            "leave": false,
            "pricing_Storage_Transfer": 0,
            "max_RAM_curr": 0.016290144490539848,
            "pricing_RAM": 5,
            "pricing_data_sent": 0.01,
            "pricing_StartRequest": 4e-07
        },
        "provider_4": {
            "name": "aws",
            "estimated_latency": [
                6.898342004956611,
                3.08410382983651,
                1.2283059977652089,
                8.010150580222954,
                0.0,
                0.7992983793496264,
                0.8526270033563194,
                5.686681908480385,
                9.963216208609238,
                7.009831982845437,
                8.682651862906742,
                9.240265682247777,
                1.7403953576109843,
                1.8511353189040238,
                4.812367937171895,
                0.880507542111449,
                3.2052799782151333,
                7.727852290952594,
                2.3490390441760036,
                1.4693603536067255
            ],
            "leave": false,
            "pricing_Storage_Transfer": 0,
            "max_RAM_curr": 0.4647145787361836,
            "pricing_RAM": 5,
            "pricing_data_sent": 0.01,
            "pricing_StartRequest": 4e-07
        },
        "provider_5": {
            "name": "aws",
            "estimated_latency": [
                3.071415102604752,
                9.547265978730186,
                3.288775687533392,
                9.873289365457767,
                0.7992983793496264,
                0.0,
                2.56420287549646,
                4.520945752170604,
                5.300269090326542,
                9.858387179321875,
                5.9700508032147,
                4.241951967181309,
                9.671977001725976,
                6.244205647068048,
                4.399137698158182,
                4.940067129831359,
                0.4588733916149257,
                3.638679364829859,
                1.8197038222533946,
                7.878532043604355
            ],
            "leave": false,
            "pricing_Storage_Transfer": 0,
            "max_RAM_curr": 0.31952824417196896,
            "pricing_RAM": 5,
            "pricing_data_sent": 0.01,
            "pricing_StartRequest": 4e-07
        },
        "provider_6": {
            "name": "aws",
            "estimated_latency": [
                2.224434495806129,
                6.190864162011232,
                0.6829028580977299,
                7.237073485535988,
                0.8526270033563194,
                2.56420287549646,
                0.0,
                5.1518718522943,
                0.8923796200687237,
                6.344393105698952,
                7.657456010752647,
                2.4036498627226095,
                2.162183995645644,
                6.272541337064686,
                8.602683808912493,
                0.2926035996458961,
                1.3185048754991802,
                5.844534010815379,
                4.764878549648323,
                2.5520889406760427
            ],
            "leave": false,
            "pricing_Storage_Transfer": 0,
            "max_RAM_curr": 0.332197629014257,
            "pricing_RAM": 5,
            "pricing_data_sent": 0.01,
            "pricing_StartRequest": 4e-07
        },
        "provider_7": {
            "name": "aws",
            "estimated_latency": [
                2.1857169362984155,
                5.999849787748343,
                1.2318339499227677,
                9.164290593680695,
                5.686681908480385,
                4.520945752170604,
                5.1518718522943,
                0.0,
                6.230815984338027,
                6.1928458373506325,
                7.666789980186186,
                7.631480151992797,
                2.279740030802535,
                0.7460586165821975,
                5.812348476596605,
                9.192910119753298,
                5.783704030418858,
                7.70073277927802,
                6.0126841493277245,
                8.957847296728387
            ],
            "leave": false,
            "pricing_Storage_Transfer": 0,
            "max_RAM_curr": 0.4737768598863518,
            "pricing_RAM": 5,
            "pricing_data_sent": 0.01,
            "pricing_StartRequest": 4e-07
        },
        "provider_8": {
            "name": "aws",
            "estimated_latency": [
                5.974003359921145,
                2.7423515665871196,
                1.1384306640851418,
                2.312388837597407,
                9.963216208609238,
                5.300269090326542,
                0.8923796200687237,
                6.230815984338027,
                0.0,
                7.8515529661629335,
                1.1434067334544156,
                4.079333726167034,
                1.3246978236372038,
                8.964981347427837,
                8.512950924762352,
                4.303995502282634,
                2.724405774660712,
                9.226004003652928,
                6.2181666724563645,
                0.10160345475379223
            ],
            "leave": false,
            "pricing_Storage_Transfer": 0,
            "max_RAM_curr": 0.018762640521785466,
            "pricing_RAM": 5,
            "pricing_data_sent": 0.01,
            "pricing_StartRequest": 4e-07
        },
        "provider_9": {
            "name": "aws",
            "estimated_latency": [
                2.050858512831408,
                5.316733694416127,
                3.5496839006193937,
                4.518653751519471,
                7.009831982845437,
                9.858387179321875,
                6.344393105698952,
                6.1928458373506325,
                7.8515529661629335,
                0.0,
                7.723276897071316,
                8.182386386044788,
                3.1579561004616252,
                5.631412854909795,
                3.3565384541522696,
                3.651356205023116,
                1.0047756518035462,
                3.847327939489385,
                6.632285371927608,
                4.891124628462216
            ],
            "leave": false,
            "pricing_Storage_Transfer": 0,
            "max_RAM_curr": 0.2623148487684571,
            "pricing_RAM": 5,
            "pricing_data_sent": 0.01,
            "pricing_StartRequest": 4e-07
        },
        "provider_10": {
            "name": "aws",
            "estimated_latency": [
                9.157527752297822,
                8.66751772120346,
                9.006394539031264,
                4.655016612812897,
                8.682651862906742,
                5.9700508032147,
                7.657456010752647,
                7.666789980186186,
                1.1434067334544156,
                7.723276897071316,
                0.0,
                8.001120132217602,
                8.102460696693095,
                3.8933886862876865,
                6.532263964377852,
                1.6245972188207847,
                1.7507731644990243,
                6.146678966970803,
                0.5750649545270781,
                6.5545967604946345
            ],
            "leave": false,
            "pricing_Storage_Transfer": 0,
            "max_RAM_curr": 0.05959003352685125,
            "pricing_RAM": 5,
            "pricing_data_sent": 0.01,
            "pricing_StartRequest": 4e-07
        },
        "provider_11": {
            "name": "aws",
            "estimated_latency": [
                0.11642745187870386,
                9.485317839754005,
                4.008572801325589,
                7.6888148018175695,
                9.240265682247777,
                4.241951967181309,
                2.4036498627226095,
                7.631480151992797,
                4.079333726167034,
                8.182386386044788,
                8.001120132217602,
                0.0,
                6.749050704055394,
                8.287600690177378,
                2.000621999980734,
                8.799315185176521,
                6.143340085339343,
                2.8353532770886427,
                1.076836787795193,
                1.8199239447813993
            ],
            "leave": false,
            "pricing_Storage_Transfer": 0,
            "max_RAM_curr": 0.3052687807484224,
            "pricing_RAM": 5,
            "pricing_data_sent": 0.01,
            "pricing_StartRequest": 4e-07
        },
        "provider_12": {
            "name": "aws",
            "estimated_latency": [
                8.778253456247805,
                3.275492709382568,
                0.24522460889579084,
                0.7372178222207624,
                1.7403953576109843,
                9.671977001725976,
                2.162183995645644,
                2.279740030802535,
                1.3246978236372038,
                3.1579561004616252,
                8.102460696693095,
                6.749050704055394,
                0.0,
                0.87207626057035,
                1.9512912331313523,
                9.625914758573199,
                2.980954371759277,
                6.624126915747226,
                8.440100472525351,
                0.6473678177457267
            ],
            "leave": false,
            "pricing_Storage_Transfer": 0,
            "max_RAM_curr": 0.43542475762079774,
            "pricing_RAM": 5,
            "pricing_data_sent": 0.01,
            "pricing_StartRequest": 4e-07
        },
        "provider_13": {
            "name": "aws",
            "estimated_latency": [
                4.956947445129021,
                5.2716068705493155,
                9.14990688496163,
                1.233327018747446,
                1.8511353189040238,
                6.244205647068048,
                6.272541337064686,
                0.7460586165821975,
                8.964981347427837,
                5.631412854909795,
                3.8933886862876865,
                8.287600690177378,
                0.87207626057035,
                0.0,
                1.1491131833888968,
                0.13144673521710798,
                2.3644824493989223,
                3.530073374542081,
                8.734662146094985,
                2.131554524006876
            ],
            "leave": false,
            "pricing_Storage_Transfer": 0,
            "max_RAM_curr": 0.09405103069796038,
            "pricing_RAM": 5,
            "pricing_data_sent": 0.01,
            "pricing_StartRequest": 4e-07
        },
        "provider_14": {
            "name": "aws",
            "estimated_latency": [
                0.5956995319512612,
                0.7938375308987066,
                7.604470397022694,
                5.92709641101848,
                4.812367937171895,
                4.399137698158182,
                8.602683808912493,
                5.812348476596605,
                8.512950924762352,
                3.3565384541522696,
                6.532263964377852,
                2.000621999980734,
                1.9512912331313523,
                1.1491131833888968,
                0.0,
                2.1018582764972806,
                5.576260063497092,
                0.5814627446512102,
                7.2354856675642365,
                6.205180732467264
            ],
            "leave": false,
            "pricing_Storage_Transfer": 0,
            "max_RAM_curr": 0.1876239647556646,
            "pricing_RAM": 5,
            "pricing_data_sent": 0.01,
            "pricing_StartRequest": 4e-07
        },
        "provider_15": {
            "name": "aws",
            "estimated_latency": [
                3.3330816931343876,
                6.467368830119085,
                5.325453518380833,
                0.6177142019908013,
                0.880507542111449,
                4.940067129831359,
                0.2926035996458961,
                9.192910119753298,
                4.303995502282634,
                3.651356205023116,
                1.6245972188207847,
                8.799315185176521,
                9.625914758573199,
                0.13144673521710798,
                2.1018582764972806,
                0.0,
                1.547092820766982,
                0.3431027417873914,
                6.863149426055209,
                3.4230797056741396
            ],
            "leave": false,
            "pricing_Storage_Transfer": 0,
            "max_RAM_curr": 0.21350527619631895,
            "pricing_RAM": 5,
            "pricing_data_sent": 0.01,
            "pricing_StartRequest": 4e-07
        },
        "provider_16": {
            "name": "aws",
            "estimated_latency": [
                7.41201395441531,
                5.683384715697545,
                7.453164886055443,
                2.388749542836553,
                3.2052799782151333,
                0.4588733916149257,
                1.3185048754991802,
                5.783704030418858,
                2.724405774660712,
                1.0047756518035462,
                1.7507731644990243,
                6.143340085339343,
                2.980954371759277,
                2.3644824493989223,
                5.576260063497092,
                1.547092820766982,
                0.0,
                5.415810537700962,
                9.571337258152807,
                2.398984515288785
            ],
            "leave": false,
            "pricing_Storage_Transfer": 0,
            "max_RAM_curr": 0.3078531701411697,
            "pricing_RAM": 5,
            "pricing_data_sent": 0.01,
            "pricing_StartRequest": 4e-07
        },
        "provider_17": {
            "name": "aws",
            "estimated_latency": [
                8.321044959453708,
                3.5913359401305947,
                2.8703160874485936,
                5.920805021254816,
                7.727852290952594,
                3.638679364829859,
                5.844534010815379,
                7.70073277927802,
                9.226004003652928,
                3.847327939489385,
                6.146678966970803,
                2.8353532770886427,
                6.624126915747226,
                3.530073374542081,
                0.5814627446512102,
                0.3431027417873914,
                5.415810537700962,
                0.0,
                8.48404750919334,
                7.235613164723581
            ],
            "leave": false,
            "pricing_Storage_Transfer": 0,
            "max_RAM_curr": 0.06672414229458651,
            "pricing_RAM": 5,
            "pricing_data_sent": 0.01,
            "pricing_StartRequest": 4e-07
        },
        "provider_18": {
            "name": "aws",
            "estimated_latency": [
                0.6622609517256514,
                4.49328018623961,
                5.965091116712954,
                4.600613683620065,
                2.3490390441760036,
                1.8197038222533946,
                4.764878549648323,
                6.0126841493277245,
                6.2181666724563645,
                6.632285371927608,
                0.5750649545270781,
                1.076836787795193,
                8.440100472525351,
                8.734662146094985,
                7.2354856675642365,
                6.863149426055209,
                9.571337258152807,
                8.48404750919334,
                0.0,
                3.7328274483724697
            ],
            "leave": false,
            "pricing_Storage_Transfer": 0,
            "max_RAM_curr": 0.21866205757985122,
            "pricing_RAM": 5,
            "pricing_data_sent": 0.01,
            "pricing_StartRequest": 4e-07
        },
        "provider_19": {
            "name": "aws",
            "estimated_latency": [
                7.904723505308349,
                7.413337126200206,
                6.9016572639632905,
                0.5833377533544383,
                1.4693603536067255,
                7.878532043604355,
                2.5520889406760427,
                8.957847296728387,
                0.10160345475379223,
                4.891124628462216,
                6.5545967604946345,
                1.8199239447813993,
                0.6473678177457267,
                2.131554524006876,
                6.205180732467264,
                3.4230797056741396,
                2.398984515288785,
                7.235613164723581,
                3.7328274483724697,
                0.0
            ],
            "leave": false,
            "pricing_Storage_Transfer": 0,
            "max_RAM_curr": 0.005435598539574016,
            "pricing_RAM": 5,
            "pricing_data_sent": 0.01,
            "pricing_StartRequest": 4e-07
        }
    }
}