{
    "name": "cloud_2_248",
    "num_nodes": 18,
    "num_leaves": 1,
    "providers": {
        "provider_0": {
            "name": "aws",
            "leave": true,
            "estimated_latency": [
                0.0,
                1.0464268239206895,
                6.697051771131248,
                1.5165713617804548,
                8.829374447670094,
                1.498755181733842,
                4.00040190303855,
                2.491477899594462,
                0.6799479302852217,
                3.982129695173089,
                2.3710293723652507,
                2.096015119011408,
                7.6837164375670595,
                3.3300683490892204,
                6.858724077093821,
                8.008438490230493,
                8.57165285153692,
                0.37771979290483126
            ],
            "pricing_Storage_Transfer": 0,
            "max_RAM_curr": 0.7208328148634752,
            "pricing_RAM": 5,
            "pricing_data_sent": 0.01,
            "pricing_StartRequest": 4e-07
        },
        "provider_1": {
            "name": "aws",
            "estimated_latency": [
                1.0464268239206895,
                0.0,
                2.748363102417448,
                4.687430591738175,
                3.2756072974679586,
                4.6625926563920075,
                4.690685573930815,
                8.495673021713781,
                1.2043302142365624,
                4.16650993344675,
                0.6761487010961212,
                8.18603495863153,
                1.975935677994524,
                1.9373450295442947,
                9.398011961666935,
                2.4249927055522726,
                7.7819031114491635,
                1.900062140582043
            ],
            "leave": false,
            "pricing_Storage_Transfer": 0,
            "max_RAM_curr": 1.2730288435622907,
            "pricing_RAM": 5,
            "pricing_data_sent": 0.01,
            "pricing_StartRequest": 4e-07
        },
        "provider_2": {
            "name": "aws",
            "estimated_latency": [
                6.697051771131248,
                2.748363102417448,
                0.0,
                5.560235717224378,
                4.461372266607672,
                5.8944312194675605,
                7.409197482208836,
                5.278007589569579,
                7.216004956727757,
                5.97739939502368,
                0.3871828643961418,
                6.840611402530961,
                2.5043866619360173,
                8.454847892424107,
                0.8569424779803855,
                1.1898167648810303,
                1.5848210003762355,
                6.123419297432076
            ],
            "leave": false,
            "pricing_Storage_Transfer": 0,
            "max_RAM_curr": 4.323713919300579,
            "pricing_RAM": 5,
            "pricing_data_sent": 0.01,
            "pricing_StartRequest": 4e-07
        },
        "provider_3": {
            "name": "aws",
            "estimated_latency": [
                1.5165713617804548,
                4.687430591738175,
                5.560235717224378,
                0.0,
                7.097668859546019,
                9.7178756416231,
                4.30639650228776,
                5.3790509932122275,
                4.02937230187931,
                4.443405954221016,
                7.959550304084644,
                3.818151090003848,
                2.1436484889915697,
                8.39132635814938,
                1.1287406503805197,
                7.762764296181724,
                6.9934554467498256,
                6.219398436532999
            ],
            "leave": false,
            "pricing_Storage_Transfer": 0,
            "max_RAM_curr": 0.07632649905756436,
            "pricing_RAM": 5,
            "pricing_data_sent": 0.01,
            "pricing_StartRequest": 4e-07
        },
        "provider_4": {
            "name": "aws",
            "estimated_latency": [
                8.829374447670094,
                3.2756072974679586,
                4.461372266607672,
                7.097668859546019,
                0.0,
                4.9969564538041755,
                9.724052725964446,
                1.4901272690581602,
                4.883663956154383,
                9.860185896158091,
                8.098946600662421,
                4.201443701260721,
                8.38375458898365,
                0.985841360992254,
                3.697607684872554,
                3.1019954488768597,
                7.006572316959964,
                6.690604502536526
            ],
            "leave": false,
            "pricing_Storage_Transfer": 0,
            "max_RAM_curr": 0.39164782056878633,
            "pricing_RAM": 5,
            "pricing_data_sent": 0.01,
            "pricing_StartRequest": 4e-07
        },
        "provider_5": {
            "name": "aws",
            "estimated_latency": [
                1.498755181733842,
                4.6625926563920075,
                5.8944312194675605,
                9.7178756416231,
                4.9969564538041755,
                0.0,
                1.508104078404205,
                1.8155892001729244,
                1.4019928829969808,
                9.413901268466185,
                7.450818749290023,
                4.009439803802722,
                2.6399894532517565,
                9.72439727649585,
                7.355274320157951,
                1.8766541628226627,
                8.349751052394916,
                2.1164600233957827
            ],
            "leave": false,
            "pricing_Storage_Transfer": 0,
            "max_RAM_curr": 3.8298524334843806,
            "pricing_RAM": 5,
            "pricing_data_sent": 0.01,
            "pricing_StartRequest": 4e-07
        },
        "provider_6": {
            "name": "aws",
            "estimated_latency": [
                4.00040190303855,
                4.690685573930815,
                7.409197482208836,
                4.30639650228776,
                9.724052725964446,
                1.508104078404205,
                0.0,
                2.2376339214159473,
                4.826298116343041,
                6.422044734591855,
                7.615477553380257,
                2.045756472054029,
                9.116598686918046,
                8.602547736564516,
                8.29011964718214,
                1.4350190882003926,
                2.9698951550803425,
                4.120228795595426
            ],
            "leave": false,
            "pricing_Storage_Transfer": 0,
            "max_RAM_curr": 0.44334931363162106,
            "pricing_RAM": 5,
            "pricing_data_sent": 0.01,
            "pricing_StartRequest": 4e-07
        },
        "provider_7": {
            "name": "aws",
            "estimated_latency": [
                2.491477899594462,
                8.495673021713781,
                5.278007589569579,
                5.3790509932122275,
                1.4901272690581602,
                1.8155892001729244,
                2.2376339214159473,
                0.0,
                3.5148314002643994,
                1.68682008031743,
                8.505201113651376,
                6.422894880100976,
                3.6843815377499385,
                1.490304583374376,
                1.7452411440088236,
                2.725786371626514,
                2.944399508428849,
                9.103852452447878
            ],
            "leave": false,
            "pricing_Storage_Transfer": 0,
            "max_RAM_curr": 0.26834177656429614,
            "pricing_RAM": 5,
            "pricing_data_sent": 0.01,
            "pricing_StartRequest": 4e-07
        },
        "provider_8": {
            "name": "aws",
            "estimated_latency": [
                0.6799479302852217,
                1.2043302142365624,
                7.216004956727757,
                4.02937230187931,
                4.883663956154383,
                1.4019928829969808,
                4.826298116343041,
                3.5148314002643994,
                0.0,
                2.2039515447227664,
                5.145065199438522,
                7.197412480510381,
                4.162299761831319,
                6.997974069525933,
                1.9479400144067702,
                2.7613066078210076,
                2.4362906614416113,
                5.5791074238429905
            ],
            "leave": false,
            "pricing_Storage_Transfer": 0,
            "max_RAM_curr": 5.2356406275073875,
            "pricing_RAM": 5,
            "pricing_data_sent": 0.01,
            "pricing_StartRequest": 4e-07
        },
        "provider_9": {
            "name": "aws",
            "estimated_latency": [
                3.982129695173089,
                4.16650993344675,
                5.97739939502368,
                4.443405954221016,
                9.860185896158091,
                9.413901268466185,
                6.422044734591855,
                1.68682008031743,
                2.2039515447227664,
                0.0,
                4.490202821490861,
                4.486072782786296,
                7.275684720524753,
                3.2856076729291543,
                1.2344715372797377,
                4.5199173884557,
                8.851002960060075,
                7.398502213799732
            ],
            "leave": false,
            "pricing_Storage_Transfer": 0,
            "max_RAM_curr": 2.353840874032429,
            "pricing_RAM": 5,
            "pricing_data_sent": 0.01,
            "pricing_StartRequest": 4e-07
        },
        "provider_10": {
            "name": "aws",
            "estimated_latency": [
                2.3710293723652507,
                0.6761487010961212,
                0.3871828643961418,
                7.959550304084644,
                8.098946600662421,
                7.450818749290023,
                7.615477553380257,
                8.505201113651376,
                5.145065199438522,
                4.490202821490861,
                0.0,
                4.440046868353795,
                8.755807799875045,
                4.464959739625627,
                2.4012774182873367,
                3.6861494917375457,
                8.833713258345643,
                9.110650559122707
            ],
            "leave": false,
            "pricing_Storage_Transfer": 0,
            "max_RAM_curr": 2.184059872164401,
            "pricing_RAM": 5,
            "pricing_data_sent": 0.01,
            "pricing_StartRequest": 4e-07
        },
        "provider_11": {
            "name": "aws",
            "estimated_latency": [
                2.096015119011408,
                8.18603495863153,
                6.840611402530961,
                3.818151090003848,
                4.201443701260721,
                4.009439803802722,
                2.045756472054029,
                6.422894880100976,
                7.197412480510381,
                4.486072782786296,
                4.440046868353795,
                0.0,
                6.725024368462491,
                2.737968696643423,
                6.590813408326141,
                6.6651436722634925,
                9.87918923922283,
                3.6088380776899385
            ],
            "leave": false,
            "pricing_Storage_Transfer": 0,
            "max_RAM_curr": 2.5512566805421395,
            "pricing_RAM": 5,
            "pricing_data_sent": 0.01,
            "pricing_StartRequest": 4e-07
        },
        "provider_12": {
            "name": "aws",
            "estimated_latency": [
                7.6837164375670595,
                1.975935677994524,
                2.5043866619360173,
                2.1436484889915697,
                8.38375458898365,
                2.6399894532517565,
                9.116598686918046,
                3.6843815377499385,
                4.162299761831319,
                7.275684720524753,
                8.755807799875045,
                6.725024368462491,
                0.0,
                7.280356685895121,
                3.6028099691199658,
                5.708411901605724,
                5.541335247384733,
                8.47073858361025
            ],
            "leave": false,
            "pricing_Storage_Transfer": 0,
            "max_RAM_curr": 0.9085940050059113,
            "pricing_RAM": 5,
            "pricing_data_sent": 0.01,
            "pricing_StartRequest": 4e-07
        },
        "provider_13": {
            "name": "aws",
            "estimated_latency": [
                3.3300683490892204,
                1.9373450295442947,
                8.454847892424107,
                8.39132635814938,
                0.985841360992254,
                9.72439727649585,
                8.602547736564516,
                1.490304583374376,
                6.997974069525933,
                3.2856076729291543,
                4.464959739625627,
                2.737968696643423,
                7.280356685895121,
                0.0,
                5.245305882576782,
                9.215486346433595,
                4.7597677218301175,
                3.155968057366498
            ],
            "leave": false,
            "pricing_Storage_Transfer": 0,
            "max_RAM_curr": 1.3396772529611842,
            "pricing_RAM": 5,
            "pricing_data_sent": 0.01,
            "pricing_StartRequest": 4e-07
        },
        "provider_14": {
            "name": "aws",
            "estimated_latency": [
                6.858724077093821,
                9.398011961666935,
                0.8569424779803855,
                1.1287406503805197,
                3.697607684872554,
                7.355274320157951,
                8.29011964718214,
                1.7452411440088236,
                1.9479400144067702,
                1.2344715372797377,
                2.4012774182873367,
                6.590813408326141,
                3.6028099691199658,
                5.245305882576782,
                0.0,
                0.7765994886088039,
                3.4292273044101482,
                0.9721903883997692
            ],
            "leave": false,
            "pricing_Storage_Transfer": 0,
            "max_RAM_curr": 4.139804374913447,
            "pricing_RAM": 5,
            "pricing_data_sent": 0.01,
            "pricing_StartRequest": 4e-07
        },
        "provider_15": {
            "name": "aws",
            "estimated_latency": [
                8.008438490230493,
                2.4249927055522726,
                1.1898167648810303,
                7.762764296181724,
                3.1019954488768597,
                1.8766541628226627,
                1.4350190882003926,
                2.725786371626514,
                2.7613066078210076,
                4.5199173884557,
                3.6861494917375457,
                6.6651436722634925,
                5.708411901605724,
                9.215486346433595,
                0.7765994886088039,
                0.0,
                8.800716137317016,
                8.955575791031185
            ],
            "leave": false,
            "pricing_Storage_Transfer": 0,
            "max_RAM_curr": 0.04843753721096074,
            "pricing_RAM": 5,
            "pricing_data_sent": 0.01,
            "pricing_StartRequest": 4e-07
        },
        "provider_16": {
            "name": "aws",
            "estimated_latency": [
                8.57165285153692,
                7.7819031114491635,
                1.5848210003762355,
                6.9934554467498256,
                7.006572316959964,
                8.349751052394916,
                2.9698951550803425,
                2.944399508428849,
                2.4362906614416113,
                8.851002960060075,
                8.833713258345643,
                9.87918923922283,
                5.541335247384733,
                4.7597677218301175,
                3.4292273044101482,
                8.800716137317016,
                0.0,
                2.1660748117441773
            ],
            "leave": false,
            "pricing_Storage_Transfer": 0,
            "max_RAM_curr": 0.15465290036176704,
            "pricing_RAM": 5,
            "pricing_data_sent": 0.01,
            "pricing_StartRequest": 4e-07
        },
        "provider_17": {
            "name": "aws",
            "estimated_latency": [
                0.37771979290483126,
                1.900062140582043,
                6.123419297432076,
                6.219398436532999,
                6.690604502536526,
                2.1164600233957827,
                4.120228795595426,
                9.103852452447878,
                5.5791074238429905,
                7.398502213799732,
                9.110650559122707,
                3.6088380776899385,
                8.47073858361025,
                3.155968057366498,
                0.9721903883997692,
                8.955575791031185,
                2.1660748117441773,
                0.0
            ],
            "leave": false,
            "pricing_Storage_Transfer": 0,
            "max_RAM_curr": 4.052705070574899,
            "pricing_RAM": 5,
            "pricing_data_sent": 0.01,
            "pricing_StartRequest": 4e-07
        }
    }
}